abhaypython/__init__.py
abhaypython-0.1.0.dist-info/METADATA
abhaypython-0.1.0.dist-info/WHEEL
abhaypython-0.1.0.dist-info/top_level.txt
abhaypython-0.1.0.dist-info/RECORD
