Metadata-Version: 2.1
Name: abhaypython
Version: 0.1.0
Summary: A library for finding exponentials
Author: ABHAY
Author-email: abhaysrivastva13@gmail.com
